pakk_flask/__init__.py
pakk_flask-2.0.0.dist-info/METADATA
pakk_flask-2.0.0.dist-info/RECORD
pakk_flask-2.0.0.dist-info/WHEEL
pakk_flask-2.0.0.dist-info/top_level.txt
