Metadata-Version: 2.1
Name: pakk-flask
Version: 2.0.0
Summary: Utilities for working with pakk files in a flask web application.
Home-page: https://github.com/pakk/pakk-flask
Author: Tristen Horton
Author-email: tristen@tristenhorton.com
License: UNKNOWN
Platform: UNKNOWN
Classifier: Programming Language :: Python :: 3.6
Classifier: License :: OSI Approved :: Apache Software License
Classifier: Operating System :: OS Independent
